LICENSE
MANIFEST.in
README.rst
setup.py
tox.ini
dankdungeon/__init__.py
dankdungeon/character.py
dankdungeon/config.py
dankdungeon/dungeon.py
dankdungeon/history.py
dankdungeon/monster.py
dankdungeon/namerator.py
dankdungeon/quest.py
dankdungeon/room.py
dankdungeon/villain.py
dankdungeon/worldmap.py
dankdungeon.egg-info/PKG-INFO
dankdungeon.egg-info/SOURCES.txt
dankdungeon.egg-info/dependency_links.txt
dankdungeon.egg-info/entry_points.txt
dankdungeon.egg-info/requires.txt
dankdungeon.egg-info/top_level.txt
dankdungeon/.ropeproject/config.py
dankdungeon/data/monsters.json
dankdungeon/data/related.json
dankdungeon/data/subtype_groups.json
dankdungeon/data/tag_groups.json
dankdungeon/data/tags.json
dankdungeon/data/type_groups.json
dankdungeon/names/dragonborn_first_female.txt
dankdungeon/names/dragonborn_first_male.txt
dankdungeon/names/dragonborn_last.txt
dankdungeon/names/dwarf.txt
dankdungeon/names/dwarf_part1.txt
dankdungeon/names/dwarf_part2.txt
dankdungeon/names/elf.txt
dankdungeon/names/halfling_last.txt
dankdungeon/names/human_first_female.txt
dankdungeon/names/human_first_male.txt
dankdungeon/names/human_last.txt
dankdungeon/names/orc.txt
dankdungeon/names/tiefling_first_female.txt
dankdungeon/names/tiefling_first_male.txt